README.rst
setup.py
pmap/__init__.py
pmap/core.py
pmap/helpers.py
py_pmap.egg-info/PKG-INFO
py_pmap.egg-info/SOURCES.txt
py_pmap.egg-info/dependency_links.txt
py_pmap.egg-info/requires.txt
py_pmap.egg-info/top_level.txt