Metadata-Version: 1.0
Name: py-pmap
Version: 0.1.1
Summary: Pmap package for Python-Guide.org
Home-page: https://github.com/jondot/python-pmap
Author: Dotan Nahum
Author-email: jondotan@gmail.com
License: MIT
Platform: UNKNOWN
